{"_type":"export","__export_format":4,"__export_date":"2020-10-27T02:19:43.131Z","__export_source":"insomnia.desktop.app:v2020.4.1","resources":[{"_id":"req_06123016d26943f68db5e68dbcb8ea5b","parentId":"fld_a51d7c4baaa64d019dd6f85d13f590ad","modified":1603765074744,"created":1603760460861,"url":"{{ base_url }}/projects","name":"Create","description":"","method":"POST","body":{"mimeType":"application/json","text":"{\n\t\"title\": \"Aplicativo  Native com VueJS\",\n\t\"owner\": \"Diego Fernandes\"\n}"},"parameters":[],"headers":[{"name":"Content-Type","value":"application/json","id":"pair_79a304950a1c49f4b935500ed6a9c7d7"}],"authentication":{},"metaSortKey":-1603760606287,"isPrivate":false,"settingStoreCookies":true,"settingSendCookies":true,"settingDisableRenderRequestBody":false,"settingEncodeUrl":true,"settingRebuildPath":true,"settingFollowRedirects":"global","_type":"request"},{"_id":"fld_a51d7c4baaa64d019dd6f85d13f590ad","parentId":"fld_37b0c2f233bc49d8a012389c91387cf0","modified":1603760343548,"created":1603760343548,"name":"Projects","description":"","environment":{},"environmentPropertyOrder":null,"metaSortKey":-1603760343549,"_type":"request_group"},{"_id":"fld_37b0c2f233bc49d8a012389c91387cf0","parentId":"fld_da058c051bb24986b3762aca24bab48b","modified":1603759998510,"created":1603759998510,"name":"Back-end_com_node-js","description":"","environment":{},"environmentPropertyOrder":null,"metaSortKey":-1603759998510,"_type":"request_group"},{"_id":"fld_da058c051bb24986b3762aca24bab48b","parentId":"wrk_76d6149d82aa43e09f65b0c7bcb69e3b","modified":1603759961550,"created":1603759961550,"name":"Nivel01","description":"","environment":{},"environmentPropertyOrder":null,"metaSortKey":-1603759961550,"_type":"request_group"},{"_id":"wrk_76d6149d82aa43e09f65b0c7bcb69e3b","parentId":null,"modified":1603760292263,"created":1603759946892,"name":"Bootcamp-GoStack","description":"","scope":null,"_type":"workspace"},{"_id":"req_aa7bdf22c8ea48f0a9b146a876afc5d9","parentId":"fld_a51d7c4baaa64d019dd6f85d13f590ad","modified":1603764718914,"created":1603760606236,"url":"{{ base_url }}/projects/95a94e23-e523-4561-926e-bf2c266f46c6","name":"Delete","description":"","method":"DELETE","body":{},"parameters":[],"headers":[],"authentication":{},"metaSortKey":-1603760606237,"isPrivate":false,"settingStoreCookies":true,"settingSendCookies":true,"settingDisableRenderRequestBody":false,"settingEncodeUrl":true,"settingRebuildPath":true,"settingFollowRedirects":"global","_type":"request"},{"_id":"req_10084e5916b5490fbd354e9e910909be","parentId":"fld_a51d7c4baaa64d019dd6f85d13f590ad","modified":1603765089183,"created":1603760361109,"url":"{{ base_url }}/projects","name":"List","description":"","method":"GET","body":{},"parameters":[{"name":"title","value":"React","description":"","id":"pair_db5e4a00164b494baf0edc1560a58fce","disabled":false},{"name":"owner","value":"Diego","description":"","id":"pair_ad78f41b91ab43ec866cd8840faca0e3","disabled":true},{"name":"","value":"","description":"","id":"pair_d3e25d2d3ec54fdc840b4e9b99a05e23"}],"headers":[],"authentication":{},"metaSortKey":-1603760573688,"isPrivate":false,"settingStoreCookies":true,"settingSendCookies":true,"settingDisableRenderRequestBody":false,"settingEncodeUrl":true,"settingRebuildPath":true,"settingFollowRedirects":"global","_type":"request"},{"_id":"req_6eeb8bc45fb7468da9b51f24f751c8df","parentId":"fld_a51d7c4baaa64d019dd6f85d13f590ad","modified":1603764378049,"created":1603760541139,"url":"{{ base_url }}/projects/61a87036-d04c-4a78-9f0d-163fe3bc8ea0","name":"Update","description":"","method":"PUT","body":{"mimeType":"application/json","text":"  {\n\t  \"title\": \"Front-end com ReactJS\",\n\t  \"owner\": \"Diego Fernandes\"\n  }"},"parameters":[],"headers":[{"name":"Content-Type","value":"application/json","id":"pair_7a5f472931d1433c8a1ea11812552352"}],"authentication":{},"metaSortKey":-1603760541139,"isPrivate":false,"settingStoreCookies":true,"settingSendCookies":true,"settingDisableRenderRequestBody":false,"settingEncodeUrl":true,"settingRebuildPath":true,"settingFollowRedirects":"global","_type":"request"},{"_id":"env_94360962995f182f9f0651383bc72c91b6329440","parentId":"wrk_76d6149d82aa43e09f65b0c7bcb69e3b","modified":1603759946972,"created":1603759946972,"name":"Base Environment","data":{},"dataPropertyOrder":null,"color":null,"isPrivate":false,"metaSortKey":1603759946972,"_type":"environment"},{"_id":"jar_94360962995f182f9f0651383bc72c91b6329440","parentId":"wrk_76d6149d82aa43e09f65b0c7bcb69e3b","modified":1603759946976,"created":1603759946976,"name":"Default Jar","cookies":[],"_type":"cookie_jar"},{"_id":"spc_be04730c275f4a65b43aa56c543e5aac","parentId":"wrk_76d6149d82aa43e09f65b0c7bcb69e3b","modified":1603759946898,"created":1603759946898,"fileName":"GoStack","contents":"","contentType":"yaml","_type":"api_spec"},{"_id":"env_db6c78fa78c04e2f9fa3e1238851d5c9","parentId":"env_94360962995f182f9f0651383bc72c91b6329440","modified":1603760937395,"created":1603760708422,"name":"dev","data":{"base_url":"http://localhost:3333"},"dataPropertyOrder":{"&":["base_url"]},"color":"#645dc0","isPrivate":false,"metaSortKey":1603760708422,"_type":"environment"},{"_id":"env_667cb812e9714f1c8a8667060cf1a1c5","parentId":"env_94360962995f182f9f0651383bc72c91b6329440","modified":1603761050552,"created":1603760954335,"name":"production","data":{"base_url":"http://www.projetododiego.com/api"},"dataPropertyOrder":{"&":["base_url"]},"color":"#30c026","isPrivate":false,"metaSortKey":1603760954335,"_type":"environment"}]}